src/README.md
src/__init__.py
src/chroma_client.py
src/config.py
src/models.py
src/resources.py
src/server.json
src/server.py
src/tools/__init__.py
src/tools/comments.py
src/tools/discover.py
src/tools/posts.py
src/tools/search.py
reddit_research_mcp-0.1.1.dist-info/METADATA
reddit_research_mcp-0.1.1.dist-info/WHEEL
reddit_research_mcp-0.1.1.dist-info/entry_points.txt
reddit_research_mcp-0.1.1.dist-info/licenses/LICENSE
reddit_research_mcp-0.1.1.dist-info/RECORD
