Metadata-Version: 2.4
Name: reddit-research-mcp
Version: 0.1.1
Summary: A minimal Model Context Protocol server for Reddit content access
Project-URL: Homepage, https://github.com/king-of-the-grackles/reddit-research-mcp
Project-URL: Repository, https://github.com/king-of-the-grackles/reddit-research-mcp
Project-URL: Issues, https://github.com/king-of-the-grackles/reddit-research-mcp/issues
Project-URL: Documentation, https://github.com/king-of-the-grackles/reddit-research-mcp#readme
Author-email: King of the Grackles <chris@ivester.ai>
License: MIT
License-File: LICENSE
Classifier: Development Status :: 4 - Beta
Classifier: Intended Audience :: Developers
Classifier: License :: OSI Approved :: MIT License
Classifier: Operating System :: OS Independent
Classifier: Programming Language :: Python :: 3
Classifier: Programming Language :: Python :: 3.11
Classifier: Programming Language :: Python :: 3.12
Classifier: Topic :: Software Development :: Libraries :: Python Modules
Requires-Python: >=3.11
Requires-Dist: aiohttp>=3.12.15
Requires-Dist: fastmcp>=0.8.0
Requires-Dist: openai-agents>=0.2.8
Requires-Dist: praw>=7.7.1
Requires-Dist: pydantic>=2.0.0
Requires-Dist: python-dotenv>=1.0.0
Requires-Dist: requests>=2.31.0
Requires-Dist: starlette>=0.32.0
Requires-Dist: uvicorn>=0.30.0
Provides-Extra: dev
Requires-Dist: pytest-asyncio>=0.24.0; extra == 'dev'
Requires-Dist: pytest-mock>=3.14.0; extra == 'dev'
Requires-Dist: pytest>=8.0.0; extra == 'dev'
